.bzrignore
AUTHORS.txt
COPYING.txt
Changelog
INSTALL.txt
MANIFEST.in
README.txt
setup.cfg
setup.py
winbuild.bat
Divisi.egg-info/PKG-INFO
Divisi.egg-info/SOURCES.txt
Divisi.egg-info/dependency_links.txt
Divisi.egg-info/namespace_packages.txt
Divisi.egg-info/requires.txt
Divisi.egg-info/top_level.txt
csc/__init__.py
csc/divisi/__init__.py
csc/divisi/association.py
csc/divisi/blend.py
csc/divisi/blending.py
csc/divisi/ccipca.py
csc/divisi/cnet.py
csc/divisi/crossbridge.py
csc/divisi/dict_mixin.py
csc/divisi/exceptions.py
csc/divisi/export_svdview.py
csc/divisi/flavors.py
csc/divisi/forgetful_ccipca.py
csc/divisi/graphics.py
csc/divisi/labeled_tensor.py
csc/divisi/labeled_view.py
csc/divisi/mds.py
csc/divisi/normalized_view.py
csc/divisi/ordered_set.py
csc/divisi/predict_2o.py
csc/divisi/priodict.py
csc/divisi/pt_labeled_tensor.py
csc/divisi/pt_ordered_set.py
csc/divisi/pt_tensor.py
csc/divisi/pyt_utils.py
csc/divisi/recycling_set.py
csc/divisi/semantic_network.py
csc/divisi/sliced_view.py
csc/divisi/sqltensor.py
csc/divisi/svd.py
csc/divisi/tensor.py
csc/divisi/unfolded_set.py
csc/divisi/unfolded_view.py
csc/divisi/util.py
doc/DESIGN.html
doc/DESIGN.html.sh
doc/DESIGN.txt
doc/tensor-by-matrix.txt
doc/demo/adhoc.py
doc/demo/ccipca_demo.py
doc/demo/dependency_corpus.py
doc/demo/smalldemo.py
doc/demo/vendor_only_svd.py
doc/examples/blending.py
doc/examples/crossbridge_example.py
doc/examples/index.txt
doc/examples/mds.py
doc/examples/selfblend_example.py
doc/examples/svd_test.py
doc/examples/test3d.py
doc/examples/tutorial.txt
svdlib/README
svdlib/__init__.py
svdlib/_svdlib.c
svdlib/_svdlib.pyx
svdlib/las2.c
svdlib/svdlib.c
svdlib/svdlib.h
svdlib/svdutil.c
svdlib/svdutil.h
svdlib/svdwrapper.c
svdlib/svdwrapper.h
test/performance_tests.py
test/tensor_util.py
test/test_blend.py
test/test_build_conceptnet.py
test/test_dense_svd.py
test/test_extreme_items.py
test/test_flavors.py
test/test_make.py
test/test_means.py
test/test_normalization.py
test/test_offset_svd.py
test/test_orderedset.py
test/test_pt_orderedset.py
test/test_recycling.py
test/test_semantic_network.py
test/test_svd.py
test/test_svdresults.py
test/test_tensor_dl.py
test/test_tensors.py
